b2d.libs/libgcc_s-8b50eaaa.so.1
b2d.libs/libstdc++-8baf04f9.so.6.0.28
b2d-0.7.2.dist-info/METADATA
b2d-0.7.2.dist-info/WHEEL
b2d-0.7.2.dist-info/LICENCE.txt
b2d-0.7.2.dist-info/RECORD
b2d-0.7.2.dist-info/top_level.txt
b2d/extend_collision.py
b2d/_b2d.cpython-37m-i386-linux-gnu.so
b2d/extend_world.py
b2d/extend_shapes.py
b2d/extend_math.py
b2d/__init__.py
b2d/extend_particles.py
b2d/extend_user_data.py
b2d/extend_draw.py
b2d/extend_fixture.py
b2d/plot.py
b2d/extend_batch_api.py
b2d/extend_joints.py
b2d/tools.py
b2d/extend_body.py
b2d/extend_contact.py
b2d/query_callback.py
b2d/testbed/__init__.py
b2d/testbed/testbed_base.py
b2d/testbed/backend/gui_base.py
b2d/testbed/backend/__init__.py
b2d/testbed/backend/default_backend.py
b2d/testbed/backend/matplotlib_gif_gui/matplotlib_gif_gui.py
b2d/testbed/backend/matplotlib_gif_gui/__init__.py
b2d/testbed/backend/gif_gui/__init__.py
b2d/testbed/backend/gif_gui/opencv_debug_draw.py
b2d/testbed/backend/gif_gui/gif_gui.py
b2d/testbed/backend/pygame/pygame_debug_draw.py
b2d/testbed/backend/pygame/pygame_gui.py
b2d/testbed/backend/pygame/__init__.py
b2d/testbed/backend/kivy/__init__.py
b2d/testbed/backend/kivy/kivy_gui.py
b2d/testbed/backend/kivy/kivy_debug_draw.py
b2d/testbed/backend/no_gui/__init__.py
b2d/testbed/backend/no_gui/no_gui.py
b2d/testbed/backend/jupyter/jupyter_batch_debug_draw.py
b2d/testbed/backend/jupyter/__init__.py
b2d/testbed/backend/jupyter/jupyter_gui.py
